CHANGES.txt
MANIFEST.in
README.rst
package.json
production.ini
requirements.txt
requirements_local.txt
setup.cfg
setup.py
tox.ini
Pacific.egg-info/PKG-INFO
Pacific.egg-info/SOURCES.txt
Pacific.egg-info/dependency_links.txt
Pacific.egg-info/entry_points.txt
Pacific.egg-info/not-zip-safe
Pacific.egg-info/requires.txt
Pacific.egg-info/top_level.txt
pacific/__init__.py
pacific/auth/__init__.py
pacific/auth/repository.py
pacific/cli/__init__.py
pacific/cli/initdb.py
pacific/config/__init__.py
pacific/config/errors.py
pacific/db/__init__.py
pacific/db/repository.py
pacific/plimdsl/__init__.py
pacific/plimdsl/parsers.py
pacific/static/favicon.ico
pacific/static/pyramid-small.png
pacific/static/pyramid.png
pacific/templates/pacific.plim
tests/__init__.py
tests/default_tests.py
tests/config/__init__.py
tests/config/parser_tests.py