Metadata-Version: 1.1
Name: Pacific
Version: 0.0.3
Summary: Pacific
Home-page: https://github.com/avanov/Pacific
Author: Maxim Avanov
Author-email: maxim.avanov@gmail.com
License: UNKNOWN
Keywords: web wsgi pylons pyramid
Platform: UNKNOWN
Classifier: Development Status :: 1 - Planning
Classifier: Environment :: Web Environment
Classifier: Framework :: Pyramid
Classifier: Intended Audience :: Developers
Classifier: License :: OSI Approved
Classifier: License :: OSI Approved :: MIT License
Classifier: Programming Language :: Python
Classifier: Programming Language :: Python :: 3
Classifier: Operating System :: POSIX
Classifier: Topic :: Internet :: WWW/HTTP
Classifier: Topic :: Internet :: WWW/HTTP :: WSGI :: Application
